stubgenj/__init__.py
stubgenj/__main__.py
stubgenj/_stubgenj.py
stubgenj/_version.py
stubgenj/conftest.py
stubgenj/tests/__init__.py
stubgenj/tests/test_stubtest.py
stubgenj-0.2.12.dist-info/LICENSE.txt
stubgenj-0.2.12.dist-info/METADATA
stubgenj-0.2.12.dist-info/WHEEL
stubgenj-0.2.12.dist-info/top_level.txt
stubgenj-0.2.12.dist-info/RECORD
