Metadata-Version: 2.1
Name: stubgenj
Version: 0.2.12
Summary: PEP-484 python stub generator for Java classes accessed through JPype
Home-page: https://gitlab.cern.ch/scripting-tools/stubgenj
Maintainer: CERN Accelerating Python
Maintainer-email: acc-py-support@cern.ch
License: MIT
Classifier: Programming Language :: Python :: 3
Classifier: Operating System :: OS Independent
Requires-Python: ~=3.6
License-File: LICENSE.txt
Requires-Dist: JPype1 (<2.0.dev0,>=1.2.1)
Requires-Dist: dataclasses ; python_version < "3.7"
Provides-Extra: all
Requires-Dist: JPype1 (<2.0.dev0,>=1.2.1) ; extra == 'all'
Requires-Dist: pytest ; extra == 'all'
Requires-Dist: mypy (<0.971,>=0.931) ; extra == 'all'
Requires-Dist: dataclasses ; (python_version < "3.7") and extra == 'all'
Requires-Dist: typing-extensions ; (python_version < "3.8") and extra == 'all'
Provides-Extra: core
Requires-Dist: JPype1 (<2.0.dev0,>=1.2.1) ; extra == 'core'
Requires-Dist: dataclasses ; (python_version < "3.7") and extra == 'core'
Provides-Extra: dev
Requires-Dist: pytest ; extra == 'dev'
Requires-Dist: mypy (<0.971,>=0.931) ; extra == 'dev'
Requires-Dist: typing-extensions ; (python_version < "3.8") and extra == 'dev'
Provides-Extra: test
Requires-Dist: pytest ; extra == 'test'
Requires-Dist: mypy (<0.971,>=0.931) ; extra == 'test'
Requires-Dist: typing-extensions ; (python_version < "3.8") and extra == 'test'
